cprinter/LICENSE
cprinter/README.MD
cprinter/__init__.py
cprinter/requirements.txt
cprinter/thirdparty.json
cprinter-0.12.dist-info/LICENSE.rst
cprinter-0.12.dist-info/METADATA
cprinter-0.12.dist-info/WHEEL
cprinter-0.12.dist-info/top_level.txt
cprinter-0.12.dist-info/RECORD
